[
  {
    "year": 2026,
    "date": "06/11/26 Expires 07/14/26",
    "area": "Tanana",
    "title": "Fairbanks Habitat Rehabilitation & Protection Cost-Share Program Workshop & Request For Proposals",
    "url": "https://www.adfg.alaska.gov/sf/EONR/index.cfm?ADFG=region.NR&Year=2026&NRID=4047",
    "pdf_url": ""
  },
  {
    "year": 2026,
    "date": "06/10/26 Expires 08/31/26",
    "area": "Upper Copper Upper Susitna",
    "title": "Copper River Personal Use Dip Net Salmon Fishing Schedule: \nJune 15–21",
    "url": "https://www.adfg.alaska.gov/sf/EONR/index.cfm?ADFG=region.NR&Year=2026&NRID=4045",
    "pdf_url": "https://www.adfg.alaska.gov/Static-sf/EONR/PDFs/2026/R3/3-RS-I-07-26.pdf"
  },
  {
    "year": 2026,
    "date": "06/10/26 Expires 12/31/26",
    "area": "Statewide",
    "title": "2026 Sport Fishing Regulation Update",
    "url": "https://www.adfg.alaska.gov/sf/EONR/index.cfm?ADFG=region.NR&Year=2026&NRID=4044",
    "pdf_url": "https://www.adfg.alaska.gov/static/regulations/regprocess/fisheriesboard/pdfs/2025-2026/proposals/183.pdf"
  },
  {
    "year": 2026,
    "date": "06/03/26 Expires 07/25/26",
    "area": "Kuskokwim",
    "title": "Aniak River Drainage Closed To Sport Fishing For King Salmon",
    "url": "https://www.adfg.alaska.gov/sf/EONR/index.cfm?ADFG=region.NR&Year=2026&NRID=4041",
    "pdf_url": "https://www.adfg.alaska.gov/Static-sf/EONR/PDFs/2026/R3/3-KS-V-06-26.pdf"
  },
  {
    "year": 2026,
    "date": "06/03/26 Expires 08/31/26",
    "area": "Upper Copper Upper Susitna",
    "title": "Copper River Personal Use Dip Net Salmon Fishing Schedule: \nJune 12–14",
    "url": "https://www.adfg.alaska.gov/sf/EONR/index.cfm?ADFG=region.NR&Year=2026&NRID=4040",
    "pdf_url": "https://www.adfg.alaska.gov/Static-sf/EONR/PDFs/2026/R3/3-RS-I-05-26.pdf"
  },
  {
    "year": 2026,
    "date": "05/27/26 Expires 12/31/26",
    "area": "Statewide",
    "title": "New “Slam” Fishing Challenges Recognize Angling Accomplishments",
    "url": "https://www.adfg.alaska.gov/sf/EONR/index.cfm?ADFG=region.NR&Year=2026&NRID=4035",
    "pdf_url": ""
  },
  {
    "year": 2026,
    "date": "05/13/26 Expires 12/31/26",
    "area": "Yukon",
    "title": "Yukon River Drainage Chum Salmon Sport Fishery Closed",
    "url": "https://www.adfg.alaska.gov/sf/EONR/index.cfm?ADFG=region.NR&Year=2026&NRID=4034",
    "pdf_url": "https://www.adfg.alaska.gov/Static-sf/EONR/PDFs/2026/R3/EO_Yukon_chum_3-CS-Y-04-26.docx.pdf"
  },
  {
    "year": 2026,
    "date": "05/06/26",
    "area": "Interior",
    "title": "2026 Copper River Personal Use Dip Net Salmon Fishery Preseason Schedule",
    "url": "https://www.adfg.alaska.gov/sf/EONR/index.cfm?ADFG=region.NR&Year=2026&NRID=4030",
    "pdf_url": "https://www.adfg.alaska.gov/static/applications/dcfnewsrelease/1753628175.pdf"
  },
  {
    "year": 2026,
    "date": "04/07/26 Expires 12/31/26",
    "area": "Upper Copper Upper Susitna",
    "title": "Upper Copper River King Salmon Sport Fishery Will Require New Permit In 2026",
    "url": "https://www.adfg.alaska.gov/sf/EONR/index.cfm?ADFG=region.NR&Year=2026&NRID=4022",
    "pdf_url": ""
  },
  {
    "year": 2026,
    "date": "02/18/26 Expires 09/30/26",
    "area": "Yukon",
    "title": "Yukon River Drainage Closed To Sport Fishing For King Salmon",
    "url": "https://www.adfg.alaska.gov/sf/EONR/index.cfm?ADFG=region.NR&Year=2026&NRID=3996",
    "pdf_url": "https://www.adfg.alaska.gov/Static-sf/EONR/PDFs/2026/R3/EO 3-KS-Y-01-26.pdf"
  },
  {
    "year": 2026,
    "date": "02/18/26 Expires 09/30/26",
    "area": "Tanana",
    "title": "Tanana River Drainage King Salmon Sport Fishery Closed",
    "url": "https://www.adfg.alaska.gov/sf/EONR/index.cfm?ADFG=region.NR&Year=2026&NRID=3997",
    "pdf_url": "https://www.adfg.alaska.gov/Static-sf/EONR/PDFs/2026/R3/EO 3-KS-U-01-26.pdf"
  },
  {
    "year": 2026,
    "date": "02/18/26 Expires 09/30/26",
    "area": "Northwest",
    "title": "Northwest Alaska King Salmon Sport Fishery Closed",
    "url": "https://www.adfg.alaska.gov/sf/EONR/index.cfm?ADFG=region.NR&Year=2026&NRID=3995",
    "pdf_url": "https://www.adfg.alaska.gov/Static-sf/EONR/PDFs/2026/R3/3-KS-W-01-26 EO.pdf"
  },
  {
    "year": 2026,
    "date": "01/05/26 Expired 02/01/26",
    "area": "Statewide",
    "title": "2026 Statewide Sport Fish Stocking Plan Open For Public Comment",
    "url": "https://www.adfg.alaska.gov/sf/EONR/index.cfm?ADFG=region.NR&Year=2026&NRID=3964",
    "pdf_url": ""
  },
  {
    "year": 2026,
    "date": "12/08/25",
    "area": "Tanana",
    "title": "Tanana River Drainage Sport Fishing Regulation Changes",
    "url": "https://www.adfg.alaska.gov/sf/EONR/index.cfm?ADFG=region.NR&Year=2026&NRID=3961",
    "pdf_url": ""
  }
]